decotra/__init__.py
decotra/s3.py
decotra-0.6.2.dist-info/WHEEL
decotra-0.6.2.dist-info/METADATA
decotra-0.6.2.dist-info/RECORD
