Metadata-Version: 2.1
Name: decotra
Version: 0.6.2
Summary: 
Author: funwarioisii
Author-email: mottirioisii@gmail.com
Requires-Python: >=3.6,<4.0
Classifier: Programming Language :: Python :: 3
Classifier: Programming Language :: Python :: 3.6
Classifier: Programming Language :: Python :: 3.7
Requires-Dist: boto3 (>=1.10,<2.0)
Requires-Dist: numpy (>=1.17,<2.0)
